restack_ai/__init__.py
restack_ai/agent.py
restack_ai/endpoints.py
restack_ai/event.py
restack_ai/function.py
restack_ai/observability.py
restack_ai/payload_codec.py
restack_ai/py.typed
restack_ai/restack.py
restack_ai/security.py
restack_ai/test_connection.py
restack_ai/utils.py
restack_ai/workflow.py
restack_ai/playground/__init__.py
restack_ai/playground/workflow.py
restack_ai-0.0.115.dist-info/METADATA
restack_ai-0.0.115.dist-info/WHEEL
restack_ai-0.0.115.dist-info/entry_points.txt
restack_ai-0.0.115.dist-info/RECORD
