Metadata-Version: 2.4
Name: restack_ai
Version: 0.0.115
Summary: Restack AI library
Author-email: Restack Team <service@restack.io>
Requires-Python: >=3.10
Requires-Dist: aiohttp<4,>=3.11.10
Requires-Dist: asyncio<4,>=3.4.3
Requires-Dist: msgspec<0.19,>=0.18.6
Requires-Dist: pydantic<3,>=2.10.6
Requires-Dist: python-dotenv<2,>=1.0.1
Requires-Dist: temporalio<2,>=1.18.1
Requires-Dist: typing-extensions>=4.12.2
Requires-Dist: websockets<15,>=13.1
